jonascript/__init__.py
jonascript/jonascript.py
jonascript-0.0.14.dist-info/METADATA
jonascript-0.0.14.dist-info/WHEEL
jonascript-0.0.14.dist-info/licenses/LICENSE
jonascript-0.0.14.dist-info/RECORD
